{
  "as_of_kst": "2026-06-12 20:13 KST",
  "as_of_date": "2026-06-12",
  "as_of_weekday": "FRI",
  "build_unix": 1781262807,
  "indexes": {
    "sp500": {
      "key": "sp500",
      "symbol": "^GSPC",
      "name": "S&P 500",
      "region": "USA",
      "kind": "broad",
      "price": 7394.3,
      "change": 127.31,
      "change_pct": 1.75,
      "spark": [
        7383.74,
        7405.73,
        7386.65,
        7266.99,
        7394.3
      ],
      "as_of": "2026-06-11"
    },
    "nasdaq": {
      "key": "nasdaq",
      "symbol": "^IXIC",
      "name": "NASDAQ Composite",
      "region": "USA",
      "kind": "tech",
      "price": 25809.66,
      "change": 640.16,
      "change_pct": 2.54,
      "spark": [
        25709.43,
        25929.66,
        25678.82,
        25169.5,
        25809.66
      ],
      "as_of": "2026-06-11"
    },
    "dow": {
      "key": "dow",
      "symbol": "^DJI",
      "name": "Dow Jones 30",
      "region": "USA",
      "kind": "value",
      "price": 50848.75,
      "change": 929.97,
      "change_pct": 1.86,
      "spark": [
        50866.78,
        50786.01,
        50872.11,
        49918.78,
        50848.75
      ],
      "as_of": "2026-06-11"
    },
    "kospi": {
      "key": "kospi",
      "symbol": "^KS11",
      "name": "KOSPI",
      "region": "KOREA",
      "kind": "broad",
      "price": 8123.62,
      "change": 359.67,
      "change_pct": 4.63,
      "spark": [
        7484.41,
        8096.93,
        7730.82,
        7763.95,
        8123.62
      ],
      "as_of": "2026-06-12"
    },
    "nikkei": {
      "key": "nikkei",
      "symbol": "^N225",
      "name": "Nikkei 225",
      "region": "JAPAN",
      "kind": "broad",
      "price": 66020.04,
      "change": 1802.77,
      "change_pct": 2.81,
      "spark": [
        64024.6,
        65416.63,
        64179.27,
        64217.27,
        66020.04
      ],
      "as_of": "2026-06-12"
    },
    "hangseng": {
      "key": "hangseng",
      "symbol": "^HSI",
      "name": "Hang Seng",
      "region": "HONG KONG",
      "kind": "broad",
      "price": 24718.1,
      "change": 468.81,
      "change_pct": 1.93,
      "spark": [
        24657.06,
        24565.9,
        24407.96,
        24249.29,
        24718.1
      ],
      "as_of": "2026-06-12"
    },
    "csi300": {
      "key": "csi300",
      "symbol": "000300.SS",
      "name": "CSI 300",
      "region": "CHINA",
      "kind": "broad",
      "price": 4777.32,
      "change": 54.91,
      "change_pct": 1.16,
      "spark": [
        4713.64,
        4801.81,
        4748.59,
        4722.41,
        4777.32
      ],
      "as_of": "2026-06-12"
    },
    "ftse": {
      "key": "ftse",
      "symbol": "^FTSE",
      "name": "FTSE 100",
      "region": "UK",
      "kind": "broad",
      "price": 10412.99,
      "change": 109.09,
      "change_pct": 1.06,
      "spark": [
        10373.2,
        10227.3,
        10254.8,
        10303.9,
        10412.99
      ],
      "as_of": "2026-06-12"
    },
    "dax": {
      "key": "dax",
      "symbol": "^GDAXI",
      "name": "DAX",
      "region": "GERMANY",
      "kind": "broad",
      "price": 24584.04,
      "change": 374.33,
      "change_pct": 1.55,
      "spark": [
        24616.22,
        24433.06,
        24195.31,
        24209.71,
        24584.04
      ],
      "as_of": "2026-06-12"
    }
  },
  "fx": {
    "USDKRW": {
      "key": "USDKRW",
      "pair": "USD/KRW",
      "rate": 1519.88,
      "kind": "direct"
    },
    "USDJPY": {
      "key": "USDJPY",
      "pair": "USD/JPY",
      "rate": 160.16,
      "kind": "direct"
    },
    "EURUSD": {
      "key": "EURUSD",
      "pair": "EUR/USD",
      "rate": 1.1577,
      "kind": "inverse"
    },
    "USDCNY": {
      "key": "USDCNY",
      "pair": "USD/CNY",
      "rate": 6.7617,
      "kind": "direct"
    },
    "DXY": {
      "key": "DXY",
      "pair": "DXY",
      "rate": 99.76,
      "change": -0.1,
      "change_pct": -0.1,
      "kind": "index"
    }
  },
  "commodities": {
    "wti": {
      "key": "wti",
      "symbol": "CL=F",
      "name": "WTI Crude",
      "unit": "$",
      "price": 84.7,
      "change": -3.01,
      "change_pct": -3.43
    },
    "gold": {
      "key": "gold",
      "symbol": "GC=F",
      "name": "Gold",
      "unit": "$",
      "price": 4230.5,
      "change": 140.2,
      "change_pct": 3.43
    },
    "btc": {
      "key": "btc",
      "symbol": "BTC-USD",
      "name": "Bitcoin",
      "unit": "$",
      "price": 63771.43,
      "change": 210.38,
      "change_pct": 0.33
    },
    "ust10y": {
      "key": "ust10y",
      "symbol": "^TNX",
      "name": "10Y UST Yield",
      "unit": "%",
      "price": 4.46,
      "change": -0.08,
      "change_pct": -1.74
    },
    "vix": {
      "key": "vix",
      "symbol": "^VIX",
      "name": "VIX",
      "unit": "",
      "price": 19.18,
      "change": -0.26,
      "change_pct": -1.34
    }
  },
  "headlines_raw": [
    {
      "source": "CNBC Markets",
      "title": "Buy AMD shares as graphics chip sales boost earnings, says Citi",
      "url": "https://www.cnbc.com/2026/06/12/buy-amd-shares-as-graphics-chip-sales-boost-earnings-says-citi.html",
      "published": "Fri, 12 Jun 2026 10:36:07 GMT"
    },
    {
      "source": "CNBC Markets",
      "title": "Friday's big stock stories: What’s likely to move the market in the next trading session",
      "url": "https://www.cnbc.com/2026/06/11/fridays-big-stock-stories-whats-likely-to-move-the-market.html",
      "published": "Thu, 11 Jun 2026 23:44:13 GMT"
    },
    {
      "source": "CNBC Markets",
      "title": "What energy insiders in DC are saying about oil prices and a possible Iran deal",
      "url": "https://www.cnbc.com/2026/06/11/what-energy-insiders-in-dc-are-saying-about-oil-prices-and-a-possible-iran-deal.html",
      "published": "Thu, 11 Jun 2026 21:29:14 GMT"
    },
    {
      "source": "CNBC Markets",
      "title": "SpaceX cuts retail IPO allocation to low 20% range, source says",
      "url": "https://www.cnbc.com/2026/06/11/spacex-cuts-retail-ipo-allocation-to-low-20percent-range-source-says.html",
      "published": "Thu, 11 Jun 2026 22:21:47 GMT"
    },
    {
      "source": "CNBC Markets",
      "title": "Pimco is warning about a spike in defaults — How it says income investors should position portfolios",
      "url": "https://www.cnbc.com/2026/06/11/pimco-is-warning-about-a-spike-in-defaults-how-to-position-portfolios.html",
      "published": "Thu, 11 Jun 2026 19:48:15 GMT"
    },
    {
      "source": "CNBC Markets",
      "title": "From startup to $1.8 trillion: The investors who took a chance on SpaceX now reap the rewards",
      "url": "https://www.cnbc.com/2026/06/11/spacex-investors-reap-rewards-1-8-trillion-valuation.html",
      "published": "Fri, 12 Jun 2026 09:49:53 GMT"
    },
    {
      "source": "Yahoo Finance",
      "title": "The 7 best crypto exchanges in 2026: Our top picks after hands-on testing",
      "url": "https://finance.yahoo.com/personal-finance/investing/article/best-crypto-exchanges-154453640.html",
      "published": "2026-04-07T15:44:53Z"
    },
    {
      "source": "Yahoo Finance",
      "title": "What to do when your pay raises aren't keeping up with inflation",
      "url": "https://finance.yahoo.com/personal-finance/banking/article/wages-increase-not-keeping-up-with-the-cost-of-living-211948928.html",
      "published": "2026-04-13T21:19:48Z"
    },
    {
      "source": "Yahoo Finance",
      "title": "Amphastar Pharmaceuticals Pivots to Proprietary Drugs, Biosimilars for Growth",
      "url": "https://finance.yahoo.com/sectors/healthcare/articles/amphastar-pharmaceuticals-pivots-proprietary-drugs-230811024.html",
      "published": "2026-06-10T23:08:11Z"
    },
    {
      "source": "Yahoo Finance",
      "title": "Paradigm and Hyperliquid Policy Center Push Back on GENIUS Act Stablecoin Rule",
      "url": "https://finance.yahoo.com/markets/crypto/articles/paradigm-hyperliquid-policy-center-push-231400196.html",
      "published": "2026-06-10T23:14:00Z"
    },
    {
      "source": "Yahoo Finance",
      "title": "These 2 Dividend Stocks Just Boosted Their Payouts by 13% — And More Income Growth Could Be Ahead",
      "url": "https://finance.yahoo.com/markets/stocks/articles/2-dividend-stocks-just-boosted-233002233.html",
      "published": "2026-06-10T23:30:02Z"
    },
    {
      "source": "Yahoo Finance",
      "title": "Why Jefferies Recommends Riot Platforms Inc (RIOT) Stock",
      "url": "https://finance.yahoo.com/markets/stocks/articles/why-jefferies-recommends-riot-platforms-233310946.html",
      "published": "2026-06-10T23:33:10Z"
    },
    {
      "source": "MarketWatch Top",
      "title": "Oil prices extend declines on possible U.S.-Iran peace deal to reopen Strait of Hormuz",
      "url": "https://www.marketwatch.com/story/oil-prices-extend-declines-on-possible-u-s-iran-peace-deal-to-reopen-strait-of-hormuz-6d2822bd?mod=mw_rss_topstories",
      "published": "Fri, 12 Jun 2026 11:10:00 GMT"
    },
    {
      "source": "MarketWatch Top",
      "title": "‘I have no experience with investing’: I inherited $2,000. I’m 42 with two children. What should I do with this money?",
      "url": "https://www.marketwatch.com/story/i-have-no-experience-with-investing-i-inherited-2-000-im-42-with-two-children-what-should-i-do-with-this-money-7b0de230?mod=mw_rss_topstories",
      "published": "Fri, 12 Jun 2026 11:00:00 GMT"
    },
    {
      "source": "MarketWatch Top",
      "title": "Why a Fed communications ‘blackout’ isn’t coming to markets under new Warsh regime",
      "url": "https://www.marketwatch.com/story/why-a-fed-communications-blackout-isnt-coming-to-markets-under-new-warsh-regime-4cfcff68?mod=mw_rss_topstories",
      "published": "Fri, 12 Jun 2026 11:00:00 GMT"
    },
    {
      "source": "MarketWatch Top",
      "title": "Here’s what could be SpaceX’s biggest upside surprise, according to a leading Silicon Valley investor",
      "url": "https://www.marketwatch.com/story/heres-what-could-be-spacexs-biggest-upside-surprise-according-to-a-leading-silicon-valley-investor-e6cab034?mod=mw_rss_topstories",
      "published": "Fri, 12 Jun 2026 10:51:00 GMT"
    },
    {
      "source": "MarketWatch Top",
      "title": "‘It seems too good to be true’: At a steak-dinner retirement seminar, the guy said annuities can outperform the market. Is that true?",
      "url": "https://www.marketwatch.com/story/it-seems-too-good-to-be-true-at-a-steak-dinner-retirement-seminar-the-guy-said-annuities-can-outperform-the-market-is-that-true-33e11b0a?mod=mw_rss_topstories",
      "published": "Fri, 12 Jun 2026 10:36:00 GMT"
    },
    {
      "source": "MarketWatch Top",
      "title": "‘We are comfortable financially’: My husband is in his 60s and has $500,000 life insurance. Is this a good time to cancel?",
      "url": "https://www.marketwatch.com/story/we-pay-100-per-month-my-husband-is-in-his-mid-60s-and-has-a-500-000-life-insurance-policy-is-it-time-to-cancel-it-4cc49ffe?mod=mw_rss_topstories",
      "published": "Fri, 12 Jun 2026 10:06:00 GMT"
    },
    {
      "source": "Investing.com News",
      "title": "Why is New Oriental Education & Technology stock rallying 4% today?",
      "url": "https://www.investing.com/news/stock-market-news/why-is-new-oriental-education--technology-stock-rallying-4-today-93CH-4739339",
      "published": "2026-06-12 10:58:39"
    },
    {
      "source": "Investing.com News",
      "title": "Guggenheim reiterates Buy on StubHub stock, cites World Cup boost",
      "url": "https://www.investing.com/news/analyst-ratings/guggenheim-reiterates-buy-on-stubhub-stock-cites-world-cup-boost-93CH-4739334",
      "published": "2026-06-12 10:55:17"
    },
    {
      "source": "Investing.com News",
      "title": "Lucid Capital Markets initiates Core Scientific stock with buy rating",
      "url": "https://www.investing.com/news/analyst-ratings/lucid-capital-markets-initiates-core-scientific-stock-with-buy-rating-93CH-4739333",
      "published": "2026-06-12 10:55:11"
    },
    {
      "source": "Investing.com News",
      "title": "Why is SailPoint stock down 2% today?",
      "url": "https://www.investing.com/news/stock-market-news/why-is-sailpoint-stock-down-2-today-93CH-4739327",
      "published": "2026-06-12 10:54:56"
    },
    {
      "source": "Investing.com News",
      "title": "UK economy contracts in April amid energy price pressures",
      "url": "https://www.investing.com/news/economic-indicators/uk-economy-contracts-in-april-amid-energy-price-pressures-4738958",
      "published": "2026-06-12 10:54:08"
    },
    {
      "source": "Investing.com News",
      "title": "Europe stocks on course to recover war-led losses on U.S.-Iran peace hopes",
      "url": "https://www.investing.com/news/stock-market-news/european-stocks-jump-to-twoweek-highs-as-iranus-peace-hopes-lift-sentiment-4738936",
      "published": "2026-06-12 10:53:19"
    },
    {
      "source": "Bloomberg Markets",
      "title": "Oil and Gas Decline on Optimism US and Iran Are Close to a Deal",
      "url": "https://www.bloomberg.com/news/articles/2026-06-11/latest-oil-market-news-and-analysis-for-june-12",
      "published": "Thu, 11 Jun 2026 22:04:43 GMT"
    },
    {
      "source": "Bloomberg Markets",
      "title": "China Firm Gets Kenya Airport Deal After Adani Fallout",
      "url": "https://www.bloomberg.com/news/articles/2026-06-11/china-firm-secures-kenya-airport-revamp-deal-after-adani-fallout",
      "published": "Thu, 11 Jun 2026 07:04:42 GMT"
    },
    {
      "source": "Bloomberg Markets",
      "title": "Banks Line Up €1.7 Billion Debt for Triton’s Flender Buyout",
      "url": "https://www.bloomberg.com/news/articles/2026-06-12/banks-line-up-1-7-billion-of-debt-for-triton-s-flender-buyout",
      "published": "Fri, 12 Jun 2026 09:20:41 GMT"
    },
    {
      "source": "Bloomberg Markets",
      "title": "Credit Traders Unwind a $20 Billion Wartime Short in Europe",
      "url": "https://www.bloomberg.com/news/articles/2026-06-12/credit-traders-unwind-a-20-billion-wartime-short-in-europe",
      "published": "Fri, 12 Jun 2026 10:48:16 GMT"
    },
    {
      "source": "Bloomberg Markets",
      "title": "Stocks Rally Further as US-Iran Deal Draws Closer: Markets Wrap",
      "url": "https://www.bloomberg.com/news/articles/2026-06-11/asian-stocks-to-gain-as-trump-signals-us-iran-deal-markets-wrap",
      "published": "Thu, 11 Jun 2026 22:03:20 GMT"
    },
    {
      "source": "Bloomberg Markets",
      "title": "UK Power Prices Turn Negative as Renewables Set to Flood Grid",
      "url": "https://www.bloomberg.com/news/articles/2026-06-12/uk-power-prices-turn-negative-as-renewables-set-to-flood-grid",
      "published": "Fri, 12 Jun 2026 10:39:07 GMT"
    }
  ],
  "summary": {
    "headlines": [
      {
        "title_ko": "美 CPI 서프라이즈에도 S&P 500·나스닥 사상최고 마감, 테크가 견인",
        "source": "CNBC",
        "url": "https://www.cnbc.com/2026/05/13/stock-market-today.html",
        "time_label": "23:00"
      },
      {
        "title_ko": "연준, 인플레 둔화 흐름 속 추가 인하 경로 유지 관측",
        "source": "Reuters",
        "url": "https://www.reuters.com/markets/us/fed-rate-cut-2026/",
        "time_label": "21:30"
      },
      {
        "title_ko": "삼성전자 CXL 메모리 양산 발표에 KOSPI 7,844 사상최고",
        "source": "Bloomberg",
        "url": "https://www.bloomberg.com/news/articles/2026-05-14/kospi-record",
        "time_label": "15:30"
      },
      {
        "title_ko": "BOJ, 임금·물가 사이클 강화 시 추가 정상화 가능 시사",
        "source": "Bank of Japan",
        "url": "https://www.boj.or.jp/en/announcements/2026/",
        "time_label": "10:00"
      },
      {
        "title_ko": "英 1Q GDP 컨센서스 부합, 스타머 정치 리스크는 여전",
        "source": "FT",
        "url": "https://www.ft.com/content/uk-gdp-2026q1",
        "time_label": "17:00"
      }
    ],
    "market_summary_ko": "미국 인플레이션 경계감에도 테크 모멘텀이 지수를 끌어올렸고, 아시아 세션에서는 삼성전자 CXL 모멘텀에 KOSPI가 다시 사상최고를 갈아엎었다. Fed 인하 vs BOJ 인상 디버전스가 달러 강세를 떠받치는 가운데, 다음 분기점은 5/21 NVDA 실적이다.",
    "risk_sentiment": "RISK-ON"
  }
}