{
  "as_of_kst": "2026-06-01 07:31 KST",
  "as_of_date": "2026-06-01",
  "as_of_weekday": "MON",
  "build_unix": 1780266717,
  "indexes": {
    "sp500": {
      "key": "sp500",
      "symbol": "^GSPC",
      "name": "S&P 500",
      "region": "USA",
      "kind": "broad",
      "price": 7580.06,
      "change": 16.43,
      "change_pct": 0.22,
      "spark": [
        7473.47,
        7519.12,
        7520.36,
        7563.63,
        7580.06
      ],
      "as_of": "2026-05-29"
    },
    "nasdaq": {
      "key": "nasdaq",
      "symbol": "^IXIC",
      "name": "NASDAQ Composite",
      "region": "USA",
      "kind": "tech",
      "price": 26972.62,
      "change": 55.15,
      "change_pct": 0.2,
      "spark": [
        26343.97,
        26656.18,
        26674.73,
        26917.47,
        26972.62
      ],
      "as_of": "2026-05-29"
    },
    "dow": {
      "key": "dow",
      "symbol": "^DJI",
      "name": "Dow Jones 30",
      "region": "USA",
      "kind": "value",
      "price": 51032.46,
      "change": 363.49,
      "change_pct": 0.72,
      "spark": [
        50579.7,
        50461.68,
        50644.28,
        50668.97,
        51032.46
      ],
      "as_of": "2026-05-29"
    },
    "kospi": {
      "key": "kospi",
      "symbol": "^KS11",
      "name": "KOSPI",
      "region": "KOREA",
      "kind": "broad",
      "price": 8476.15,
      "change": 290.86,
      "change_pct": 3.55,
      "spark": [
        7847.71,
        8047.51,
        8228.7,
        8185.29,
        8476.15
      ],
      "as_of": "2026-05-29"
    },
    "nikkei": {
      "key": "nikkei",
      "symbol": "^N225",
      "name": "Nikkei 225",
      "region": "JAPAN",
      "kind": "broad",
      "price": 66329.5,
      "change": 1636.38,
      "change_pct": 2.53,
      "spark": [
        65158.19,
        64996.09,
        64999.41,
        64693.12,
        66329.5
      ],
      "as_of": "2026-05-29"
    },
    "hangseng": {
      "key": "hangseng",
      "symbol": "^HSI",
      "name": "Hang Seng",
      "region": "HONG KONG",
      "kind": "broad",
      "price": 25182.39,
      "change": 176.23,
      "change_pct": 0.7,
      "spark": [
        25606.03,
        25599.45,
        25328.23,
        25006.16,
        25182.39
      ],
      "as_of": "2026-05-29"
    },
    "csi300": {
      "key": "csi300",
      "symbol": "000300.SS",
      "name": "CSI 300",
      "region": "CHINA",
      "kind": "broad",
      "price": 4892.12,
      "change": -22.09,
      "change_pct": -0.45,
      "spark": [
        4921.6,
        4947.85,
        4908.17,
        4914.21,
        4892.12
      ],
      "as_of": "2026-05-29"
    },
    "ftse": {
      "key": "ftse",
      "symbol": "^FTSE",
      "name": "FTSE 100",
      "region": "UK",
      "kind": "broad",
      "price": 10409.3,
      "change": -16.7,
      "change_pct": -0.16,
      "spark": [
        10466.3,
        10491.4,
        10505.0,
        10426.0,
        10409.3
      ],
      "as_of": "2026-05-29"
    },
    "dax": {
      "key": "dax",
      "symbol": "^GDAXI",
      "name": "DAX",
      "region": "GERMANY",
      "kind": "broad",
      "price": 25104.7,
      "change": 12.45,
      "change_pct": 0.05,
      "spark": [
        25389.1,
        25184.89,
        25177.8,
        25092.25,
        25104.7
      ],
      "as_of": "2026-05-29"
    }
  },
  "fx": {
    "USDKRW": {
      "key": "USDKRW",
      "pair": "USD/KRW",
      "rate": 1507.38,
      "kind": "direct"
    },
    "USDJPY": {
      "key": "USDJPY",
      "pair": "USD/JPY",
      "rate": 159.4,
      "kind": "direct"
    },
    "EURUSD": {
      "key": "EURUSD",
      "pair": "EUR/USD",
      "rate": 1.1658,
      "kind": "inverse"
    },
    "USDCNY": {
      "key": "USDCNY",
      "pair": "USD/CNY",
      "rate": 6.7657,
      "kind": "direct"
    },
    "DXY": {
      "key": "DXY",
      "pair": "DXY",
      "rate": 98.99,
      "change": 0.08,
      "change_pct": 0.08,
      "kind": "index"
    }
  },
  "commodities": {
    "wti": {
      "key": "wti",
      "symbol": "CL=F",
      "name": "WTI Crude",
      "unit": "$",
      "price": 89.76,
      "change": 2.4,
      "change_pct": 2.75
    },
    "gold": {
      "key": "gold",
      "symbol": "GC=F",
      "name": "Gold",
      "unit": "$",
      "price": 4565.0,
      "change": 4.5,
      "change_pct": 0.1
    },
    "btc": {
      "key": "btc",
      "symbol": "BTC-USD",
      "name": "Bitcoin",
      "unit": "$",
      "price": 73758.01,
      "change": 3.17,
      "change_pct": 0.0
    },
    "ust10y": {
      "key": "ust10y",
      "symbol": "^TNX",
      "name": "10Y UST Yield",
      "unit": "%",
      "price": 4.45,
      "change": -0.0,
      "change_pct": -0.04
    },
    "vix": {
      "key": "vix",
      "symbol": "^VIX",
      "name": "VIX",
      "unit": "",
      "price": 15.32,
      "change": -0.42,
      "change_pct": -2.67
    }
  },
  "headlines_raw": [
    {
      "source": "CNBC Markets",
      "title": "Top Wall Street analysts see robust growth potential in these 3 stocks",
      "url": "https://www.cnbc.com/2026/05/31/top-wall-street-analysts-see-robust-growth-potential-in-these-3-stocks.html",
      "published": "Sun, 31 May 2026 11:50:08 GMT"
    },
    {
      "source": "CNBC Markets",
      "title": "Micron is one of the most overbought stocks after this week’s rally to new highs",
      "url": "https://www.cnbc.com/2026/05/30/micron-is-one-of-the-most-overbought-stocks-after-this-weeks-rally-to-new-highs.html",
      "published": "Sat, 30 May 2026 13:04:29 GMT"
    },
    {
      "source": "CNBC Markets",
      "title": "Berkshire trails red-hot S&P 500 by biggest margin so far this year",
      "url": "https://www.cnbc.com/2026/05/30/berkshire-trails-red-hot-sp-500-by-biggest-margin-so-far-this-year.html",
      "published": "Sat, 30 May 2026 12:47:51 GMT"
    },
    {
      "source": "CNBC Markets",
      "title": "Morgan Stanley says these 'dividend hopefuls' are poised to outperform if they initiate a payout",
      "url": "https://www.cnbc.com/2026/05/29/morgan-stanley-says-these-dividend-hopefuls-are-poised-to-outperform-if-they-initiate-a-payout.html",
      "published": "Fri, 29 May 2026 19:00:01 GMT"
    },
    {
      "source": "CNBC Markets",
      "title": "Software stocks are crashing up. Here are the winners",
      "url": "https://www.cnbc.com/2026/05/29/software-stocks-are-crashing-up-here-are-the-winners.html",
      "published": "Fri, 29 May 2026 18:07:35 GMT"
    },
    {
      "source": "CNBC Markets",
      "title": "Dell shocks Wall Street with booming AI server sales. Where analysts see it headed next",
      "url": "https://www.cnbc.com/2026/05/29/dell-shocked-street-on-booming-q1-server-sales-analysts-weigh-in.html",
      "published": "Fri, 29 May 2026 16:24:48 GMT"
    },
    {
      "source": "Yahoo Finance",
      "title": "Warren Buffett's Berkshire dumps entire stake in dividend stock",
      "url": "https://finance.yahoo.com/markets/stocks/articles/warren-buffetts-berkshire-dumps-entire-203300760.html",
      "published": "2026-05-30T20:33:00Z"
    },
    {
      "source": "Yahoo Finance",
      "title": "BOJ may heed calls to pause bond taper next year",
      "url": "https://finance.yahoo.com/economy/policy/articles/analysis-boj-may-heed-calls-064926660.html",
      "published": "2026-05-31T22:11:42Z"
    },
    {
      "source": "Yahoo Finance",
      "title": "Dow Jones Futures Fall As Trump Makes This Iran Move; Nvidia, Tesla Lead 5 Titans Near Buy Points",
      "url": "https://www.investors.com/market-trend/stock-market-today/dow-jones-futures-iran-hopes-nvidia-tesla-stocks-near-buy-points/?src=A00220&yptr=yahoo",
      "published": "2026-05-31T22:07:19Z"
    },
    {
      "source": "Yahoo Finance",
      "title": "Seagate Technology Holdings plc (STX): Leopold Aschenbrenner Sells Stake",
      "url": "https://finance.yahoo.com/markets/stocks/articles/seagate-technology-holdings-plc-stx-220222184.html",
      "published": "2026-05-31T22:02:22Z"
    },
    {
      "source": "Yahoo Finance",
      "title": "Western Digital Corporation (WDC): Leopold Aschenbrenner Is Selling This Stock",
      "url": "https://finance.yahoo.com/markets/stocks/articles/western-digital-corporation-wdc-leopold-220142206.html",
      "published": "2026-05-31T22:01:42Z"
    },
    {
      "source": "Yahoo Finance",
      "title": "Nvidia’s latest product is a game-changer",
      "url": "https://finance.yahoo.com/markets/stocks/articles/nvidia-latest-product-game-changer-010300358.html",
      "published": "2026-05-31T01:03:00Z"
    },
    {
      "source": "MarketWatch Top",
      "title": "Oil rises, U.S. stock futures dip as Wall Street looks to extend its winning streak",
      "url": "https://www.marketwatch.com/story/oil-rises-u-s-stock-futures-dip-as-wall-street-looks-to-extend-its-winning-streak-2490f216?mod=mw_rss_topstories",
      "published": "Sun, 31 May 2026 22:17:00 GMT"
    },
    {
      "source": "MarketWatch Top",
      "title": "The stock index you invest in isn’t always the most important decision. Here’s what matters even more.",
      "url": "https://www.marketwatch.com/story/investing-in-the-dow-or-s-p-500-doesnt-matter-heres-what-actually-does-757aa571?mod=mw_rss_topstories",
      "published": "Sun, 31 May 2026 20:08:00 GMT"
    },
    {
      "source": "MarketWatch Top",
      "title": "Government is now an active investor — and it’s why your portfolio needs ‘home-court advantage’",
      "url": "https://www.marketwatch.com/story/the-u-s-china-rivalry-is-killing-global-supply-chains-your-portfolio-needs-a-home-court-advantage-02870253?mod=mw_rss_topstories",
      "published": "Sun, 31 May 2026 20:02:00 GMT"
    },
    {
      "source": "MarketWatch Top",
      "title": "It’s not just tech stocks: The broad-based strength of the market right now gives investors reason to stay the course",
      "url": "https://www.marketwatch.com/story/its-not-just-tech-stocks-the-broad-based-strength-of-the-market-right-now-gives-investors-reason-to-stay-the-course-4ef65de3?mod=mw_rss_topstories",
      "published": "Sun, 31 May 2026 19:12:00 GMT"
    },
    {
      "source": "MarketWatch Top",
      "title": "Here’s what’s worth streaming in June 2026 on Netflix, Hulu, HBO Max and more",
      "url": "https://www.marketwatch.com/story/heres-whats-worth-streaming-in-june-2026-on-netflix-hulu-hbo-max-and-more-7c73c539?mod=mw_rss_topstories",
      "published": "Sun, 31 May 2026 16:00:00 GMT"
    },
    {
      "source": "MarketWatch Top",
      "title": "Here’s how Gap’s yoga-wear maker Athleta went from must-have to ‘generic’",
      "url": "https://www.marketwatch.com/story/heres-how-gaps-yoga-wear-maker-athleta-went-from-must-have-to-generic-3d94b008?mod=mw_rss_topstories",
      "published": "Sun, 31 May 2026 14:00:00 GMT"
    },
    {
      "source": "Investing.com News",
      "title": "Colombia right wing candidate De La Espriella, leftist Cepeda poised for run-off",
      "url": "https://www.investing.com/news/economy-news/colombians-weigh-leftistreforms-against-rightwing-crackdowns-in-presidential-vote-4717841",
      "published": "2026-05-31 22:12:57"
    },
    {
      "source": "Investing.com News",
      "title": "Trump to headline 250th anniversary fair opening after performers drop out",
      "url": "https://www.investing.com/news/world-news/trump-considers-dropping-concerts-in-us-capital-after-artists-drop-out-4717774",
      "published": "2026-05-31 22:00:32"
    },
    {
      "source": "Investing.com News",
      "title": "Pentagon chief sounds ’alarm’ over China’s buildup, urges allies to boost defence spend",
      "url": "https://www.investing.com/news/economy-news/pentagon-chief-sounds-alarm-over-chinas-buildup-urges-allies-to-boost-defence-spend-4717948",
      "published": "2026-05-31 21:54:30"
    },
    {
      "source": "Investing.com News",
      "title": "Russia stocks lower at close of trade; MOEX Russia Index unchanged",
      "url": "https://www.investing.com/news/stock-market-news/russia-stocks-lower-at-close-of-trade-moex-russia-index-unchanged-4717947",
      "published": "2026-05-31 21:20:04"
    },
    {
      "source": "Investing.com News",
      "title": "German infrastructure fund misses its spending targets, Handelsblatt says",
      "url": "https://www.investing.com/news/economy-news/german-infrastructure-fund-misses-its-spending-targets-handelsblatt-says-4717946",
      "published": "2026-05-31 20:54:44"
    },
    {
      "source": "Bloomberg Markets",
      "title": "Oil Climbs as US-Iran Ceasefire Remains Elusive: Markets Wrap",
      "url": "https://www.bloomberg.com/news/articles/2026-05-31/oil-climbs-as-us-iran-ceasefire-remains-elusive-markets-wrap",
      "published": "Sun, 31 May 2026 22:10:32 GMT"
    },
    {
      "source": "Bloomberg Markets",
      "title": "Oil Rises From Six-Week Low Amid Uncertainty Over US-Iran Deal",
      "url": "https://www.bloomberg.com/news/articles/2026-05-31/latest-oil-market-news-and-analysis-for-june-1",
      "published": "Sun, 31 May 2026 22:02:15 GMT"
    },
    {
      "source": "Bloomberg Markets",
      "title": "Berkshire Hathaway to Buy Taylor Morrison for $6.8 Billion",
      "url": "https://www.bloomberg.com/news/articles/2026-05-31/berkshire-hathaway-to-buy-taylor-morrison-for-6-8-billion",
      "published": "Sun, 31 May 2026 20:40:05 GMT"
    },
    {
      "source": "Bloomberg Markets",
      "title": "Petrobras Cuts Diesel Prices Amid Federal Subsidy Plan",
      "url": "https://www.bloomberg.com/news/articles/2026-05-31/petrobras-cuts-diesel-prices-amid-federal-subsidy-plan",
      "published": "Sun, 31 May 2026 21:35:03 GMT"
    },
    {
      "source": "Bloomberg Markets",
      "title": "Wall Street Risk Rally Powers Past War Stalemate",
      "url": "https://www.bloomberg.com/news/articles/2026-05-31/wall-street-risk-rally-powers-past-war-stalemate-markets-wrap",
      "published": "Sun, 31 May 2026 19:29:04 GMT"
    },
    {
      "source": "Bloomberg Markets",
      "title": "Billionaire Hotelier Wants to Take Japan’s APA Global",
      "url": "https://www.bloomberg.com/news/videos/2026-05-31/billionaire-hotelier-wants-to-take-japan-s-apa-global-video",
      "published": "Sun, 31 May 2026 21:00:10 GMT"
    },
    {
      "source": "FT Markets",
      "title": "Ritz-Carlton Yacht lenders ease terms to keep luxury cruise line afloat",
      "url": "https://www.ft.com/content/bc435fa9-05f7-4c1b-81fa-9ba9628fc629",
      "published": "Sun, 31 May 2026 17:00:02 GMT"
    }
  ],
  "summary": {
    "headlines": [
      {
        "title_ko": "美 CPI 서프라이즈에도 S&P 500·나스닥 사상최고 마감, 테크가 견인",
        "source": "CNBC",
        "url": "https://www.cnbc.com/2026/05/13/stock-market-today.html",
        "time_label": "23:00"
      },
      {
        "title_ko": "연준, 인플레 둔화 흐름 속 추가 인하 경로 유지 관측",
        "source": "Reuters",
        "url": "https://www.reuters.com/markets/us/fed-rate-cut-2026/",
        "time_label": "21:30"
      },
      {
        "title_ko": "삼성전자 CXL 메모리 양산 발표에 KOSPI 7,844 사상최고",
        "source": "Bloomberg",
        "url": "https://www.bloomberg.com/news/articles/2026-05-14/kospi-record",
        "time_label": "15:30"
      },
      {
        "title_ko": "BOJ, 임금·물가 사이클 강화 시 추가 정상화 가능 시사",
        "source": "Bank of Japan",
        "url": "https://www.boj.or.jp/en/announcements/2026/",
        "time_label": "10:00"
      },
      {
        "title_ko": "英 1Q GDP 컨센서스 부합, 스타머 정치 리스크는 여전",
        "source": "FT",
        "url": "https://www.ft.com/content/uk-gdp-2026q1",
        "time_label": "17:00"
      }
    ],
    "market_summary_ko": "미국 인플레이션 경계감에도 테크 모멘텀이 지수를 끌어올렸고, 아시아 세션에서는 삼성전자 CXL 모멘텀에 KOSPI가 다시 사상최고를 갈아엎었다. Fed 인하 vs BOJ 인상 디버전스가 달러 강세를 떠받치는 가운데, 다음 분기점은 5/21 NVDA 실적이다.",
    "risk_sentiment": "RISK-ON"
  }
}