{
  "as_of_kst": "2026-06-22 22:11 KST",
  "as_of_date": "2026-06-22",
  "as_of_weekday": "MON",
  "build_unix": 1782133915,
  "indexes": {
    "sp500": {
      "key": "sp500",
      "symbol": "^GSPC",
      "name": "S&P 500",
      "region": "USA",
      "kind": "broad",
      "price": 7500.58,
      "change": 80.48,
      "change_pct": 1.08,
      "spark": [
        7431.46,
        7554.29,
        7511.35,
        7420.1,
        7500.58
      ],
      "as_of": "2026-06-18"
    },
    "nasdaq": {
      "key": "nasdaq",
      "symbol": "^IXIC",
      "name": "NASDAQ Composite",
      "region": "USA",
      "kind": "tech",
      "price": 26517.93,
      "change": 496.27,
      "change_pct": 1.91,
      "spark": [
        25888.84,
        26683.94,
        26376.34,
        26021.66,
        26517.93
      ],
      "as_of": "2026-06-18"
    },
    "dow": {
      "key": "dow",
      "symbol": "^DJI",
      "name": "Dow Jones 30",
      "region": "USA",
      "kind": "value",
      "price": 51564.7,
      "change": 72.15,
      "change_pct": 0.14,
      "spark": [
        51202.26,
        51671.03,
        51999.67,
        51492.55,
        51564.7
      ],
      "as_of": "2026-06-18"
    },
    "kospi": {
      "key": "kospi",
      "symbol": "^KS11",
      "name": "KOSPI",
      "region": "KOREA",
      "kind": "broad",
      "price": 9114.55,
      "change": 62.13,
      "change_pct": 0.69,
      "spark": [
        8726.6,
        8864.24,
        9063.84,
        9052.42,
        9114.55
      ],
      "as_of": "2026-06-22"
    },
    "nikkei": {
      "key": "nikkei",
      "symbol": "^N225",
      "name": "Nikkei 225",
      "region": "JAPAN",
      "kind": "broad",
      "price": 72353.96,
      "change": 1103.9,
      "change_pct": 1.55,
      "spark": [
        69404.5,
        69902.25,
        71053.49,
        71250.06,
        72353.96
      ],
      "as_of": "2026-06-22"
    },
    "hangseng": {
      "key": "hangseng",
      "symbol": "^HSI",
      "name": "Hang Seng",
      "region": "HONG KONG",
      "kind": "broad",
      "price": 23768.52,
      "change": -156.29,
      "change_pct": -0.65,
      "spark": [
        24842.67,
        24493.95,
        24312.16,
        23924.81,
        23768.52
      ],
      "as_of": "2026-06-22"
    },
    "csi300": {
      "key": "csi300",
      "symbol": "000300.SS",
      "name": "CSI 300",
      "region": "CHINA",
      "kind": "broad",
      "price": 5059.66,
      "change": 118.06,
      "change_pct": 2.39,
      "spark": [
        4891.71,
        4884.23,
        4931.39,
        4941.6,
        5059.66
      ],
      "as_of": "2026-06-22"
    },
    "ftse": {
      "key": "ftse",
      "symbol": "^FTSE",
      "name": "FTSE 100",
      "region": "UK",
      "kind": "broad",
      "price": 10423.86,
      "change": 60.56,
      "change_pct": 0.58,
      "spark": [
        10494.2,
        10508.6,
        10399.7,
        10363.3,
        10423.86
      ],
      "as_of": "2026-06-22"
    },
    "dax": {
      "key": "dax",
      "symbol": "^GDAXI",
      "name": "DAX",
      "region": "GERMANY",
      "kind": "broad",
      "price": 25029.57,
      "change": 43.75,
      "change_pct": 0.18,
      "spark": [
        24910.41,
        24934.67,
        25026.8,
        24985.82,
        25029.57
      ],
      "as_of": "2026-06-22"
    }
  },
  "fx": {
    "USDKRW": {
      "key": "USDKRW",
      "pair": "USD/KRW",
      "rate": 1536.8199,
      "kind": "direct"
    },
    "USDJPY": {
      "key": "USDJPY",
      "pair": "USD/JPY",
      "rate": 161.75,
      "kind": "direct"
    },
    "EURUSD": {
      "key": "EURUSD",
      "pair": "EUR/USD",
      "rate": 1.1448,
      "kind": "inverse"
    },
    "USDCNY": {
      "key": "USDCNY",
      "pair": "USD/CNY",
      "rate": 6.7639,
      "kind": "direct"
    },
    "DXY": {
      "key": "DXY",
      "pair": "DXY",
      "rate": 100.97,
      "change": 0.12,
      "change_pct": 0.12,
      "kind": "index"
    }
  },
  "commodities": {
    "wti": {
      "key": "wti",
      "symbol": "CL=F",
      "name": "WTI Crude",
      "unit": "$",
      "price": 74.76,
      "change": -1.84,
      "change_pct": -2.4
    },
    "gold": {
      "key": "gold",
      "symbol": "GC=F",
      "name": "Gold",
      "unit": "$",
      "price": 4210.8,
      "change": -13.3,
      "change_pct": -0.31
    },
    "btc": {
      "key": "btc",
      "symbol": "BTC-USD",
      "name": "Bitcoin",
      "unit": "$",
      "price": 65072.54,
      "change": 1835.0,
      "change_pct": 2.9
    },
    "ust10y": {
      "key": "ust10y",
      "symbol": "^TNX",
      "name": "10Y UST Yield",
      "unit": "%",
      "price": 4.49,
      "change": 0.04,
      "change_pct": 0.94
    },
    "vix": {
      "key": "vix",
      "symbol": "^VIX",
      "name": "VIX",
      "unit": "",
      "price": 17.06,
      "change": 0.66,
      "change_pct": 4.02
    }
  },
  "headlines_raw": [
    {
      "source": "CNBC Markets",
      "title": "This AI connectivity play nearly doubled in 2026. Evercore ISI says it has more room to run",
      "url": "https://www.cnbc.com/2026/06/22/credo-technology-nearly-doubled-in-2026-evercore-isi-says-gains-ahead.html",
      "published": "Mon, 22 Jun 2026 12:00:26 GMT"
    },
    {
      "source": "CNBC Markets",
      "title": "This chip equipment giant has outperformed in 2026. Bank of America sees even more gains",
      "url": "https://www.cnbc.com/2026/06/22/this-chip-equipment-giant-has-outperformed-in-2026-bank-of-america-sees-even-more-gains.html",
      "published": "Mon, 22 Jun 2026 11:21:27 GMT"
    },
    {
      "source": "CNBC Markets",
      "title": "This oil and gas stock has been under pressure. Wells Fargo says it can jump more than 50%",
      "url": "https://www.cnbc.com/2026/06/22/this-oil-and-gas-stock-has-struggled-wells-fargo-says-it-may-bounce.html",
      "published": "Mon, 22 Jun 2026 10:48:06 GMT"
    },
    {
      "source": "CNBC Markets",
      "title": "Top Wall Street analysts like these 3 dividend stocks for solid returns",
      "url": "https://www.cnbc.com/2026/06/21/top-wall-street-analysts-like-these-3-dividend-stocks-for-solid-returns.html",
      "published": "Sun, 21 Jun 2026 11:19:06 GMT"
    },
    {
      "source": "CNBC Markets",
      "title": "Five top tech stocks with major upside, Bank of America says",
      "url": "https://www.cnbc.com/2026/06/20/five-top-tech-stocks-with-major-upside-bank-of-america-says.html",
      "published": "Sat, 20 Jun 2026 11:00:47 GMT"
    },
    {
      "source": "CNBC Markets",
      "title": "Goldman Sachs is betting that a recent merger will drive sharp gains for this travel stock",
      "url": "https://www.cnbc.com/2026/06/20/goldman-sachs-bets-a-recent-merger-will-drive-sharp-gains-for-this-travel-stock.html",
      "published": "Sat, 20 Jun 2026 11:04:17 GMT"
    },
    {
      "source": "Yahoo Finance",
      "title": "After closing 1,000 restaurants, seafood chain sees clear sailing",
      "url": "https://finance.yahoo.com/small-business/articles/closing-1-000-restaurants-seafood-011700497.html",
      "published": "2026-06-22T01:17:00Z"
    },
    {
      "source": "Yahoo Finance",
      "title": "Silver prices today, Monday, June 22, 2026: Silver prices rebound to Friday levels",
      "url": "https://finance.yahoo.com/personal-finance/investing/article/silver-prices-today-monday-june-22-2026-silver-prices-rebound-to-friday-levels-125923781.html",
      "published": "2026-06-22T12:59:23Z"
    },
    {
      "source": "Yahoo Finance",
      "title": "Stock market today: S&P 500, Nasdaq, Dow futures muted with peace talks, AI demand in focus",
      "url": "https://finance.yahoo.com/markets/stocks/live/stock-market-today-monday-june-22-225817825.html",
      "published": "2026-06-21T22:58:17Z"
    },
    {
      "source": "Yahoo Finance",
      "title": "Micron stock surges amid memory trade boom",
      "url": "https://finance.yahoo.com/markets/article/micron-stock-surges-amid-memory-trade-boom-125205263.html",
      "published": "2026-06-22T12:52:05Z"
    },
    {
      "source": "Yahoo Finance",
      "title": "Robinhood’s (HOOD) Workforce Cut Raised Eyebrows But Wall Street Is Focusing on Something Else",
      "url": "https://finance.yahoo.com/markets/stocks/articles/robinhood-hood-workforce-cut-raised-125048685.html",
      "published": "2026-06-22T12:50:48Z"
    },
    {
      "source": "Yahoo Finance",
      "title": "Analyst Report: Illinois Tool Works Inc",
      "url": "https://finance.yahoo.com/research/reports/ARGUS_3094_AnalystReport_1782125786000?yptr=yahoo&ncid=yahooproperties_plusresear_nm5q6ze1cei",
      "published": "2026-06-22T10:56:26Z"
    },
    {
      "source": "MarketWatch Top",
      "title": "Former Federal Reserve chairman Alan Greenspan dies at 100",
      "url": "https://www.marketwatch.com/story/former-federal-reserve-chairman-alan-greenspan-dies-a7a4030d?mod=mw_rss_topstories",
      "published": "Mon, 22 Jun 2026 12:44:00 GMT"
    },
    {
      "source": "MarketWatch Top",
      "title": "‘Money can make you happy’: My wife and I have no heirs, but we’re making the world a better place by giving it away",
      "url": "https://www.marketwatch.com/story/money-can-make-you-happy-my-wife-and-i-have-no-heirs-but-were-making-the-world-a-better-place-by-giving-it-away-f61fad98?mod=mw_rss_topstories",
      "published": "Mon, 22 Jun 2026 12:30:00 GMT"
    },
    {
      "source": "MarketWatch Top",
      "title": "Trump ‘jawboning’ has masked a global oil-supply disaster, and the reality could mean $135 crude, says industry veteran",
      "url": "https://www.marketwatch.com/story/trump-jawboning-has-masked-a-global-oil-supply-disaster-and-the-reality-could-mean-135-crude-says-industry-veteran-9b0bb52b?mod=mw_rss_topstories",
      "published": "Mon, 22 Jun 2026 12:26:00 GMT"
    },
    {
      "source": "MarketWatch Top",
      "title": "The secret to wellness is simple: Eat this breakfast and work out at the right time",
      "url": "https://www.marketwatch.com/story/the-secret-to-wellness-is-simple-eat-this-breakfast-and-work-out-at-the-right-time-43c696b9?mod=mw_rss_topstories",
      "published": "Mon, 22 Jun 2026 12:16:00 GMT"
    },
    {
      "source": "MarketWatch Top",
      "title": "China’s new economic drivers: a sad toy elf and a robot police force",
      "url": "https://www.marketwatch.com/story/chinas-new-economic-drivers-a-sad-toy-elf-and-a-robot-police-force-8759daf9?mod=mw_rss_topstories",
      "published": "Mon, 22 Jun 2026 12:09:00 GMT"
    },
    {
      "source": "MarketWatch Top",
      "title": "‘I’ll probably be working until I die’: I’m 60, work as a waiter and have $2,000 in a Roth IRA. What will happen to me?",
      "url": "https://www.marketwatch.com/story/ill-probably-be-working-until-i-die-im-60-work-as-a-restaurant-server-and-have-2-000-in-an-ira-who-can-help-me-6e36253a?mod=mw_rss_topstories",
      "published": "Mon, 22 Jun 2026 12:07:00 GMT"
    },
    {
      "source": "Investing.com News",
      "title": "InterCure secures $7.4M funding commitment, may rise to $18.6M",
      "url": "https://www.investing.com/news/company-news/intercure-secures-74m-funding-commitment-may-rise-to-186m-93CH-4752759",
      "published": "2026-06-22 12:57:45"
    },
    {
      "source": "Investing.com News",
      "title": "Ondas stock rises on $40M defense orders in June",
      "url": "https://www.investing.com/news/stock-market-news/ondas-stock-rises-on-40m-defense-orders-in-june-93CH-4752758",
      "published": "2026-06-22 12:56:50"
    },
    {
      "source": "Investing.com News",
      "title": "Alan Greenspan, US Fed ’maestro’ through years of boom and bust, dies at 100",
      "url": "https://www.investing.com/news/economy-news/alan-greenspan-economist-and-longtime-head-of-the-federal-reserve-dies-at-100-nbc-news-reports-4752313",
      "published": "2026-06-22 12:56:02"
    },
    {
      "source": "Investing.com News",
      "title": "Goldman Sachs says EV surge may cut oil demand by late 2027",
      "url": "https://www.investing.com/news/economy-news/goldman-sachs-says-ev-surge-may-cut-oil-demand-by-late-2027-4752734",
      "published": "2026-06-22 12:55:39"
    },
    {
      "source": "Investing.com News",
      "title": "Uber-backed Lime seeks up to $1.66 billion valuation in US IPO",
      "url": "https://www.investing.com/news/stock-market-news/uberbacked-lime-aims-to-raise-up-to-1809-million-in-us-ipo-4752278",
      "published": "2026-06-22 12:55:05"
    },
    {
      "source": "Investing.com News",
      "title": "York water co president & ceo Joseph Hand buys $738 in shares",
      "url": "https://www.investing.com/news/insider-trading-news/york-water-co-president--ceo-joseph-hand-buys-738-in-shares-93CH-4752757",
      "published": "2026-06-22 12:55:01"
    },
    {
      "source": "Bloomberg Markets",
      "title": "Lagarde Sees No Need for More Forceful ECB Response to War",
      "url": "https://www.bloomberg.com/news/articles/2026-06-22/lagarde-sees-no-need-for-more-forceful-ecb-response-to-iran-war",
      "published": "Mon, 22 Jun 2026 13:00:00 GMT"
    },
    {
      "source": "Bloomberg Markets",
      "title": "Mexico Is Tapping Global Debt Markets to Fund Bond Buyback",
      "url": "https://www.bloomberg.com/news/articles/2026-06-22/mexico-is-tapping-global-debt-markets-to-fund-bond-buyback",
      "published": "Mon, 22 Jun 2026 12:51:04 GMT"
    },
    {
      "source": "Bloomberg Markets",
      "title": "Europe Heat Wave Sends Power Prices Soaring as Alerts Spread",
      "url": "https://www.bloomberg.com/news/articles/2026-06-22/europe-s-heat-wave-intensifies-with-france-on-red-alert",
      "published": "Mon, 22 Jun 2026 08:02:28 GMT"
    },
    {
      "source": "Bloomberg Markets",
      "title": "Oil Declines After US-Iran Peace Talks Show Signs of Progress",
      "url": "https://www.bloomberg.com/news/articles/2026-06-21/latest-oil-market-news-and-analysis-for-june-22",
      "published": "Sun, 21 Jun 2026 22:02:25 GMT"
    },
    {
      "source": "Bloomberg Markets",
      "title": "Bond Traders Plot Impact of Next UK Chancellor With Starmer Out",
      "url": "https://www.bloomberg.com/news/articles/2026-06-22/bond-traders-want-to-know-who-manages-the-money-with-starmer-out",
      "published": "Mon, 22 Jun 2026 12:39:30 GMT"
    },
    {
      "source": "Bloomberg Markets",
      "title": "RBC Says Stocks Can Weather Fed Hikes, But Not Too Many",
      "url": "https://www.bloomberg.com/news/videos/2026-06-22/rbc-says-stocks-can-weather-fed-hikes-but-not-too-many-video",
      "published": "Mon, 22 Jun 2026 12:32:36 GMT"
    }
  ],
  "summary": {
    "headlines": [
      {
        "title_ko": "美 CPI 서프라이즈에도 S&P 500·나스닥 사상최고 마감, 테크가 견인",
        "source": "CNBC",
        "url": "https://www.cnbc.com/2026/05/13/stock-market-today.html",
        "time_label": "23:00"
      },
      {
        "title_ko": "연준, 인플레 둔화 흐름 속 추가 인하 경로 유지 관측",
        "source": "Reuters",
        "url": "https://www.reuters.com/markets/us/fed-rate-cut-2026/",
        "time_label": "21:30"
      },
      {
        "title_ko": "삼성전자 CXL 메모리 양산 발표에 KOSPI 7,844 사상최고",
        "source": "Bloomberg",
        "url": "https://www.bloomberg.com/news/articles/2026-05-14/kospi-record",
        "time_label": "15:30"
      },
      {
        "title_ko": "BOJ, 임금·물가 사이클 강화 시 추가 정상화 가능 시사",
        "source": "Bank of Japan",
        "url": "https://www.boj.or.jp/en/announcements/2026/",
        "time_label": "10:00"
      },
      {
        "title_ko": "英 1Q GDP 컨센서스 부합, 스타머 정치 리스크는 여전",
        "source": "FT",
        "url": "https://www.ft.com/content/uk-gdp-2026q1",
        "time_label": "17:00"
      }
    ],
    "market_summary_ko": "미국 인플레이션 경계감에도 테크 모멘텀이 지수를 끌어올렸고, 아시아 세션에서는 삼성전자 CXL 모멘텀에 KOSPI가 다시 사상최고를 갈아엎었다. Fed 인하 vs BOJ 인상 디버전스가 달러 강세를 떠받치는 가운데, 다음 분기점은 5/21 NVDA 실적이다.",
    "risk_sentiment": "RISK-ON"
  }
}